prolothar_rule_mining/__init__.py
prolothar_rule_mining/models/__init__.py
prolothar_rule_mining/models/conditions.cp311-win_amd64.pyd
prolothar_rule_mining/models/conditions.cpp
prolothar_rule_mining/models/conditions.pxd
prolothar_rule_mining/models/conditions.pyx
prolothar_rule_mining/models/converter/eventflow_graph_to_pm4py_petrinet_converter.py
prolothar_rule_mining/models/converter/sequence_to_class_dataset_converter.py
prolothar_rule_mining/models/converter/sequence_to_multilabel_dataset_converter.py
prolothar_rule_mining/models/dataset_generator/__init__.py
prolothar_rule_mining/models/dataset_generator/classification.py
prolothar_rule_mining/models/dataset_generator/data_to_sequence.py
prolothar_rule_mining/models/dataset_generator/dataset_generator.py
prolothar_rule_mining/models/event_flow_graph/__init__.pxd
prolothar_rule_mining/models/event_flow_graph/__init__.py
prolothar_rule_mining/models/event_flow_graph/caching.py
prolothar_rule_mining/models/event_flow_graph/edge.py
prolothar_rule_mining/models/event_flow_graph/graph.py
prolothar_rule_mining/models/event_flow_graph/node.cp311-win_amd64.pyd
prolothar_rule_mining/models/event_flow_graph/node.cpp
prolothar_rule_mining/models/event_flow_graph/node.pxd
prolothar_rule_mining/models/event_flow_graph/node.pyx
prolothar_rule_mining/models/event_flow_graph/alignment/__init__.py
prolothar_rule_mining/models/event_flow_graph/alignment/a_star.cp311-win_amd64.pyd
prolothar_rule_mining/models/event_flow_graph/alignment/a_star.cpp
prolothar_rule_mining/models/event_flow_graph/alignment/a_star.pyx
prolothar_rule_mining/models/event_flow_graph/alignment/alignment.cp311-win_amd64.pyd
prolothar_rule_mining/models/event_flow_graph/alignment/alignment.cpp
prolothar_rule_mining/models/event_flow_graph/alignment/alignment.pxd
prolothar_rule_mining/models/event_flow_graph/alignment/alignment.pyx
prolothar_rule_mining/models/event_flow_graph/alignment/alignment_finder.cp311-win_amd64.pyd
prolothar_rule_mining-3.0.2.dist-info/LICENSE
prolothar_rule_mining-3.0.2.dist-info/METADATA
prolothar_rule_mining-3.0.2.dist-info/WHEEL
prolothar_rule_mining-3.0.2.dist-info/top_level.txt
prolothar_rule_mining-3.0.2.dist-info/RECORD
