Metadata-Version: 2.1
Name: prolothar-rule-mining
Version: 3.0.2
Summary: algorithms for prediction and rule mining on event sequences
Home-page: https://github.com/shs-it/prolothar-rule-mining
Author: Boris Wiegand
Author-email: boris.wiegand@stahl-holding-saar.de
Classifier: Programming Language :: Python :: 3
Classifier: Programming Language :: Python :: 3.11
License-File: LICENSE
Requires-Dist: pyfim ==6.28
Requires-Dist: lightgbm ==3.1.1
Requires-Dist: beautifulsoup4 ==4.9.3
Requires-Dist: depq ==1.5.5
Requires-Dist: strsimpy ==0.1.3
Requires-Dist: lime ==0.2.0.1
Requires-Dist: mixed-naive-bayes ==0.0.1
